{
	"info": {
		"_postman_id": "7561d13e-7fa8-4dde-91b1-869ba66c33e4",
		"name": "TC11 DELETE ID Invalid NEGATIVE",
		"schema": "https://schema.getpostman.com/json/collection/v2.1.0/collection.json",
		"_exporter_id": "26426910",
		"_collection_link": "https://www.postman.com/warped-station-759745/workspace/api-pnm/collection/26426910-7561d13e-7fa8-4dde-91b1-869ba66c33e4?action=share&source=collection_link&creator=26426910"
	},
	"item": [
		{
			"name": "Hapus ID yang Tidak Ada",
			"request": {
				"method": "GET",
				"header": []
			},
			"response": []
		}
	]
}